flask_login_user/__init__.py
flask_login_user/gcp/__init__.py
flask_login_user/gcp/datastore/__init__.py
flask_login_user/gcp/datastore/caching.py
flask_login_user/gcp/datastore/config.py
flask_login_user/gcp/datastore/user.py
flask_login_gcp_datastore-0.0.3.dist-info/LICENSE
flask_login_gcp_datastore-0.0.3.dist-info/METADATA
flask_login_gcp_datastore-0.0.3.dist-info/WHEEL
flask_login_gcp_datastore-0.0.3.dist-info/top_level.txt
flask_login_gcp_datastore-0.0.3.dist-info/RECORD
