Metadata-Version: 2.1
Name: flask-login-gcp-datastore
Version: 0.0.3
Summary: Implement flask-login with Google Cloud Datastore
Home-page: https://github.com/anchitarnav/flask-login-gcp-datastore
Author: Anchit Arnav
Author-email: arnavanchit@gmail.com
License: Apache Software License
Keywords: gcp datastore flask-login flask login google cloud
Platform: UNKNOWN
Classifier: Programming Language :: Python :: 3.7
Classifier: License :: OSI Approved :: Apache Software License
Classifier: Operating System :: OS Independent
Requires-Python: >=3.7
Requires-Dist: google-cloud-ndb
